owc/__init__.py
owc/http_client.py
owc/owc.py
python_owc-0.0.2.dist-info/METADATA
python_owc-0.0.2.dist-info/WHEEL
python_owc-0.0.2.dist-info/licenses/LICENSE
python_owc-0.0.2.dist-info/RECORD
