Metadata-Version: 2.4
Name: python_owc
Version: 0.0.2
Summary: Asyncronous Python Offline Web Communication
Project-URL: Homepage, https://github.com
Project-URL: Issues, https://github.com
Author-email: Fabio Antonio Astore <astore.a.fabio@gmail.com>
License-Expression: MIT
License-File: LICENSE
Requires-Python: >=3.13
Requires-Dist: aiodns==3.5.0
Requires-Dist: aiohttp==3.12.15
Requires-Dist: brotli==1.1.0
